factory_djoy/__about__.py
factory_djoy/__init__.py
factory_djoy/factories.py
factory_djoy-2.2.2.dist-info/LICENSE
factory_djoy-2.2.2.dist-info/METADATA
factory_djoy-2.2.2.dist-info/WHEEL
factory_djoy-2.2.2.dist-info/top_level.txt
factory_djoy-2.2.2.dist-info/RECORD
